{
    "position_offset": [
        -0.2,
        0.95,
        -0.45
    ],
    "scale": 1.0,
    "orientation_quat": [
        0.0,
        1.0,
        0.0,
        0.0
    ],
    "target_pos":[
        0.4,
        -0.1,
        1.35
    ],
    "keyframes": [
        250,
        1150
    ],
    "loop_amplitudes": [
        10.0,
        4.1,
        7.7
    ],
    "loop_speeds": [
        0.15,
        0.21,
        0.0165
    ],
    "loop_amplitude_std_factor": 1.1,
    "loop_speed_std_factor": 1.1
}